pitcherflask/__init__.py
pitcherflask/pitcherflask.py
pitcherflask-0.0.6.dist-info/METADATA
pitcherflask-0.0.6.dist-info/WHEEL
pitcherflask-0.0.6.dist-info/entry_points.txt
pitcherflask-0.0.6.dist-info/top_level.txt
pitcherflask-0.0.6.dist-info/RECORD
