Metadata-Version: 2.1
Name: pitcherflask
Version: 0.0.6
Summary: Build a basic flask project without wasting time on setup.
Home-page: http://github.com/divine-architect/pitcherflask
Author: divine-architect
Author-email: solarhatesbeing@gmail.com
License: MIT
Keywords: flask web api
Classifier: Development Status :: 1 - Planning
Classifier: Topic :: Utilities
Classifier: License :: OSI Approved :: MIT License
